casvisor/__init__.py
casvisor/base.py
casvisor/main.py
casvisor/record.py
casvisor/util.py
casvisor_python_sdk-1.0.0.dist-info/LICENSE
casvisor_python_sdk-1.0.0.dist-info/METADATA
casvisor_python_sdk-1.0.0.dist-info/WHEEL
casvisor_python_sdk-1.0.0.dist-info/top_level.txt
casvisor_python_sdk-1.0.0.dist-info/RECORD
