Metadata-Version: 2.1
Name: casvisor-python-sdk
Version: 1.0.0
Summary: Python SDK for Casvisor
Home-page: https://github.com/casvisor/casvisor-python-sdk
Author: Casvisor
Author-email: Casvisor <admin@casvisor.com>
License: Apache License
Project-URL: Home, https://github.com/casvisor/casvisor-python-sdk
Keywords: Casvisor
Platform: any
Classifier: Intended Audience :: Developers
Classifier: License :: OSI Approved :: Apache Software License
Classifier: Operating System :: OS Independent
Classifier: Programming Language :: Python
Classifier: Programming Language :: Python :: 3.8
Classifier: Programming Language :: Python :: 3.9
Classifier: Programming Language :: Python :: 3.10
Classifier: Programming Language :: Python :: 3.11
Classifier: Programming Language :: Python :: 3.12
Requires-Python: >=3.8
License-File: LICENSE
Requires-Dist: requests~=2.32.0
Requires-Dist: requests-toolbelt
Requires-Dist: requests-mock
